rag_core_lib/impl/__init__.py
rag_core_lib/impl/data_types/__init__.py
rag_core_lib/impl/data_types/content_type.py
rag_core_lib/impl/data_types/search_request.py
rag_core_lib/impl/embeddings/__init__.py
rag_core_lib/impl/embeddings/embedder.py
rag_core_lib/impl/embeddings/embedder_type.py
rag_core_lib/impl/embeddings/langchain_community_embedder.py
rag_core_lib/impl/embeddings/stackit_embedder.py
rag_core_lib/impl/langfuse_manager/__init__.py
rag_core_lib/impl/langfuse_manager/langfuse_manager.py
rag_core_lib/impl/llms/__init__.py
rag_core_lib/impl/llms/llm_factory.py
rag_core_lib/impl/llms/llm_type.py
rag_core_lib/impl/settings/__init__.py
rag_core_lib/impl/settings/embedder_class_type_settings.py
rag_core_lib/impl/settings/fake_embedder_settings.py
rag_core_lib/impl/settings/langfuse_settings.py
rag_core_lib/impl/settings/logging_settings.py
rag_core_lib/impl/settings/ollama_embedder_settings.py
rag_core_lib/impl/settings/ollama_llm_settings.py
rag_core_lib/impl/settings/rag_class_types_settings.py
rag_core_lib/impl/settings/retry_decorator_settings.py
rag_core_lib/impl/settings/stackit_embedder_settings.py
rag_core_lib/impl/settings/stackit_vllm_settings.py
rag_core_lib/impl/tracers/__init__.py
rag_core_lib/impl/tracers/langfuse_traced_runnable.py
rag_core_lib/impl/utils/__init__.py
rag_core_lib/impl/utils/async_threadsafe_semaphore.py
rag_core_lib/impl/utils/retry_decorator.py
rag_core_lib/impl/utils/utils.py
rag_core_lib/runnables/__init__.py
rag_core_lib/runnables/async_runnable.py
rag_core_lib/tracers/__init__.py
rag_core_lib/tracers/traced_runnable.py
rag_core_lib-3.4.0.dist-info/METADATA
rag_core_lib-3.4.0.dist-info/WHEEL
rag_core_lib-3.4.0.dist-info/RECORD
