Metadata-Version: 2.4
Name: rag-core-lib
Version: 3.4.0
Summary: The rag-core-lib contains the shared components of at least two of the rag libs.
License: Apache-2.0
Author: STACKIT GmbH & Co. KG
Author-email: data-ai@stackit.cloud
Maintainer: Andreas Klos
Maintainer-email: andreas.klos@stackit.cloud
Requires-Python: >=3.13,<4.0
Classifier: License :: OSI Approved :: Apache Software License
Classifier: Programming Language :: Python :: 3
Classifier: Programming Language :: Python :: 3.13
Classifier: Programming Language :: Python :: 3.14
Requires-Dist: deprecated (>=1.2.18,<2.0.0)
Requires-Dist: flashrank (>=0.2.10,<0.3.0)
Requires-Dist: langchain (>=0.3.25,<0.4.0)
Requires-Dist: langchain-community (==0.3.30)
Requires-Dist: langchain-core (==0.3.77)
Requires-Dist: langchain-openai (>=0.3.27,<0.4.0)
Requires-Dist: langfuse (==3.6.1)
Requires-Dist: oauthlib (>=3.2.2,<4.0.0)
Requires-Dist: openai (>=1.77.0,<2.0.0)
Requires-Dist: pydantic (>=2.11.4,<3.0.0)
Requires-Dist: pydantic-settings (>=2.2.1,<3.0.0)
Requires-Dist: requests-oauthlib (>=2.0.0,<3.0.0)
Project-URL: Homepage, https://pypi.org/project/rag-core-lib
Project-URL: Repository, https://github.com/stackitcloud/rag-template
